scgenome/__init__.py
scgenome/_version.py
scgenome/cncluster.py
scgenome/cnplot.py
scgenome/refgenome.py
scgenome/utils.py
scgenome/data/grch38.fa.fai
scgenome/data/grch38_cytoBand.txt.gz
scgenome/data/hg19.fa.fai
scgenome/data/hg19_cytoBand.txt.gz
scgenome/data/mm10.fa.fai
scgenome/data/mm10_cytoBand.txt.gz
scgenome/datasets/__init__.py
scgenome/datasets/_datasets.py
scgenome/datasets/data/OV2295_HMMCopy_reduced.h5ad
scgenome/datasets/data/OV_051_Medicc2_reduced.h5ad
scgenome/plotting/__init__.py
scgenome/plotting/cn.py
scgenome/plotting/cn_colors.py
scgenome/plotting/heatmap.py
scgenome/plotting/phylo.py
scgenome/plotting/qc.py
scgenome/preprocessing/__init__.py
scgenome/preprocessing/filtering.py
scgenome/preprocessing/load_cn.py
scgenome/preprocessing/load_snv.py
scgenome/preprocessing/transform.py
scgenome/tests/__init__.py
scgenome/tests/test_imports.py
scgenome/tests/test_phylo.py
scgenome/tests/test_ranges.py
scgenome/tools/__init__.py
scgenome/tools/binfeat.py
scgenome/tools/cluster.py
scgenome/tools/cntransitions.py
scgenome/tools/concat.py
scgenome/tools/genes.py
scgenome/tools/getters.py
scgenome/tools/pca.py
scgenome/tools/phylo.py
scgenome/tools/ranges.py
scgenome/tools/sorting.py
scgenome-0.0.20.dist-info/METADATA
scgenome-0.0.20.dist-info/WHEEL
scgenome-0.0.20.dist-info/top_level.txt
scgenome-0.0.20.dist-info/RECORD
