Metadata-Version: 2.1
Name: scgenome
Version: 0.0.20
Summary: Code for analyzing single cell whole genomes
Home-page: https://github.com/shahcompbio/scgenome
Author: Shah Lab
Requires-Dist: adjustText
Requires-Dist: anndata
Requires-Dist: bamread
Requires-Dist: biopython
Requires-Dist: bokeh
Requires-Dist: brewer2mpl
Requires-Dist: Click
Requires-Dist: csverve>=0.3.1
Requires-Dist: hdbscan
Requires-Dist: hmmlearn
Requires-Dist: ipython!=8.7.0
Requires-Dist: jupyter
Requires-Dist: lda
Requires-Dist: matplotlib
Requires-Dist: nose
Requires-Dist: numba
Requires-Dist: numexpr
Requires-Dist: numpy==1.23
Requires-Dist: oauthlib
Requires-Dist: pandas
Requires-Dist: pyBigWig
Requires-Dist: pyfaidx
Requires-Dist: pyranges
Requires-Dist: pysam==0.19
Requires-Dist: PyYAML
Requires-Dist: scikit-learn
Requires-Dist: scipy
Requires-Dist: seaborn
Requires-Dist: statsmodels
Requires-Dist: umap-learn
Requires-Dist: wgs-analysis
Requires-Dist: pypeliner
Requires-Dist: joblib==1.1.1
Requires-Dist: sphinx==5.1.1
Requires-Dist: requests==2.28
